README.txt
setup.cfg
setup.py
Paste-1.7.5.1-py2.7.egg/EGG-INFO/PKG-INFO
Paste-1.7.5.1-py2.7.egg/EGG-INFO/SOURCES.txt
Paste-1.7.5.1-py2.7.egg/EGG-INFO/dependency_links.txt
Paste-1.7.5.1-py2.7.egg/EGG-INFO/entry_points.txt
Paste-1.7.5.1-py2.7.egg/EGG-INFO/namespace_packages.txt
Paste-1.7.5.1-py2.7.egg/EGG-INFO/not-zip-safe
Paste-1.7.5.1-py2.7.egg/EGG-INFO/requires.txt
Paste-1.7.5.1-py2.7.egg/EGG-INFO/top_level.txt
Paste-1.7.5.1-py2.7.egg/paste/__init__.py
Paste-1.7.5.1-py2.7.egg/paste/__init__.pyc
Paste-1.7.5.1-py2.7.egg/paste/cascade.py
Paste-1.7.5.1-py2.7.egg/paste/cascade.pyc
Paste-1.7.5.1-py2.7.egg/paste/cgiapp.py
Paste-1.7.5.1-py2.7.egg/paste/cgiapp.pyc
Paste-1.7.5.1-py2.7.egg/paste/cgitb_catcher.py
Paste-1.7.5.1-py2.7.egg/paste/cgitb_catcher.pyc
Paste-1.7.5.1-py2.7.egg/paste/config.py
Paste-1.7.5.1-py2.7.egg/paste/config.pyc
Paste-1.7.5.1-py2.7.egg/paste/errordocument.py
Paste-1.7.5.1-py2.7.egg/paste/errordocument.pyc
Paste-1.7.5.1-py2.7.egg/paste/fileapp.py
Paste-1.7.5.1-py2.7.egg/paste/fileapp.pyc
Paste-1.7.5.1-py2.7.egg/paste/fixture.py
Paste-1.7.5.1-py2.7.egg/paste/fixture.pyc
Paste-1.7.5.1-py2.7.egg/paste/flup_session.py
Paste-1.7.5.1-py2.7.egg/paste/flup_session.pyc
Paste-1.7.5.1-py2.7.egg/paste/gzipper.py
Paste-1.7.5.1-py2.7.egg/paste/gzipper.pyc
Paste-1.7.5.1-py2.7.egg/paste/httpexceptions.py
Paste-1.7.5.1-py2.7.egg/paste/httpexceptions.pyc
Paste-1.7.5.1-py2.7.egg/paste/httpheaders.py
Paste-1.7.5.1-py2.7.egg/paste/httpheaders.pyc
Paste-1.7.5.1-py2.7.egg/paste/httpserver.py
Paste-1.7.5.1-py2.7.egg/paste/httpserver.pyc
Paste-1.7.5.1-py2.7.egg/paste/lint.py
Paste-1.7.5.1-py2.7.egg/paste/lint.pyc
Paste-1.7.5.1-py2.7.egg/paste/modpython.py
Paste-1.7.5.1-py2.7.egg/paste/modpython.pyc
Paste-1.7.5.1-py2.7.egg/paste/pony.py
Paste-1.7.5.1-py2.7.egg/paste/pony.pyc
Paste-1.7.5.1-py2.7.egg/paste/progress.py
Paste-1.7.5.1-py2.7.egg/paste/progress.pyc
Paste-1.7.5.1-py2.7.egg/paste/proxy.py
Paste-1.7.5.1-py2.7.egg/paste/proxy.pyc
Paste-1.7.5.1-py2.7.egg/paste/recursive.py
Paste-1.7.5.1-py2.7.egg/paste/recursive.pyc
Paste-1.7.5.1-py2.7.egg/paste/registry.py
Paste-1.7.5.1-py2.7.egg/paste/registry.pyc
Paste-1.7.5.1-py2.7.egg/paste/reloader.py
Paste-1.7.5.1-py2.7.egg/paste/reloader.pyc
Paste-1.7.5.1-py2.7.egg/paste/request.py
Paste-1.7.5.1-py2.7.egg/paste/request.pyc
Paste-1.7.5.1-py2.7.egg/paste/response.py
Paste-1.7.5.1-py2.7.egg/paste/response.pyc
PasteDeploy-1.5.0-py2.6.egg/EGG-INFO/PKG-INFO
PasteDeploy-1.5.0-py2.6.egg/EGG-INFO/SOURCES.txt
PasteDeploy-1.5.0-py2.6.egg/EGG-INFO/dependency_links.txt
PasteDeploy-1.5.0-py2.6.egg/EGG-INFO/entry_points.txt
PasteDeploy-1.5.0-py2.6.egg/EGG-INFO/namespace_packages.txt
PasteDeploy-1.5.0-py2.6.egg/EGG-INFO/not-zip-safe
PasteDeploy-1.5.0-py2.6.egg/EGG-INFO/requires.txt
PasteDeploy-1.5.0-py2.6.egg/EGG-INFO/top_level.txt
PasteDeploy-1.5.0-py2.7.egg/EGG-INFO/PKG-INFO
PasteDeploy-1.5.0-py2.7.egg/EGG-INFO/SOURCES.txt
PasteDeploy-1.5.0-py2.7.egg/EGG-INFO/dependency_links.txt
PasteDeploy-1.5.0-py2.7.egg/EGG-INFO/entry_points.txt
PasteDeploy-1.5.0-py2.7.egg/EGG-INFO/namespace_packages.txt
PasteDeploy-1.5.0-py2.7.egg/EGG-INFO/not-zip-safe
PasteDeploy-1.5.0-py2.7.egg/EGG-INFO/requires.txt
PasteDeploy-1.5.0-py2.7.egg/EGG-INFO/top_level.txt
PasteScript-1.7.5-py2.6.egg/EGG-INFO/PKG-INFO
PasteScript-1.7.5-py2.6.egg/EGG-INFO/SOURCES.txt
PasteScript-1.7.5-py2.6.egg/EGG-INFO/dependency_links.txt
PasteScript-1.7.5-py2.6.egg/EGG-INFO/entry_points.txt
PasteScript-1.7.5-py2.6.egg/EGG-INFO/namespace_packages.txt
PasteScript-1.7.5-py2.6.egg/EGG-INFO/not-zip-safe
PasteScript-1.7.5-py2.6.egg/EGG-INFO/requires.txt
PasteScript-1.7.5-py2.6.egg/EGG-INFO/top_level.txt
PasteScript-1.7.5-py2.7.egg/EGG-INFO/PKG-INFO
PasteScript-1.7.5-py2.7.egg/EGG-INFO/SOURCES.txt
PasteScript-1.7.5-py2.7.egg/EGG-INFO/dependency_links.txt
PasteScript-1.7.5-py2.7.egg/EGG-INFO/entry_points.txt
PasteScript-1.7.5-py2.7.egg/EGG-INFO/namespace_packages.txt
PasteScript-1.7.5-py2.7.egg/EGG-INFO/not-zip-safe
PasteScript-1.7.5-py2.7.egg/EGG-INFO/requires.txt
PasteScript-1.7.5-py2.7.egg/EGG-INFO/top_level.txt
ageliaco.rd2.egg-info/PKG-INFO
ageliaco.rd2.egg-info/SOURCES.txt
ageliaco.rd2.egg-info/dependency_links.txt
ageliaco.rd2.egg-info/entry_points.txt
ageliaco.rd2.egg-info/namespace_packages.txt
ageliaco.rd2.egg-info/not-zip-safe
ageliaco.rd2.egg-info/paster_plugins.txt
ageliaco.rd2.egg-info/requires.txt
ageliaco.rd2.egg-info/top_level.txt
