Metadata-Version: 1.0
Name: ageliaco.rd2
Version: 0.8.4
Summary: Product to manage project with annual cycles
Home-page: https://github.com/renfers/ageliaco.rd2
Author: Serge Renfer
Author-email: serge.renfer@gmail.com
License: GPL
Keywords: ageliaco rd project management
Platform: UNKNOWN
Classifier: Framework :: Plone
Classifier: Programming Language :: Python
Classifier: Topic :: Software Development :: Libraries :: Python Modules
